LICENSE.txt
MANIFEST.in
README.rst
setup.cfg
setup.py
txzmq/__init__.py
txzmq/connection.py
txzmq/factory.py
txzmq/pair.py
txzmq/pubsub.py
txzmq/pushpull.py
txzmq/reqrep.py
txzmq/test/__init__.py
txzmq/test/test_connection.py
txzmq/test/test_factory.py
txzmq/test/test_pair.py
txzmq/test/test_pubsub.py
txzmq/test/test_pushpull.py
txzmq/test/test_reqrep.py
vic_txZMQ.egg-info/PKG-INFO
vic_txZMQ.egg-info/SOURCES.txt
vic_txZMQ.egg-info/dependency_links.txt
vic_txZMQ.egg-info/requires.txt
vic_txZMQ.egg-info/top_level.txt