Metadata-Version: 1.0
Name: vic-txZMQ
Version: 0.5.1
Summary: Twisted bindings for ZeroMQ
Home-page: http://pypi.python.org/pypi/vic-txZMQ
Author: Victor Lin, Andrey Smirnov
Author-email: bornstub@gmail.com
License: GPLv2
Platform: UNKNOWN
